vocab_api/__init__.py
vocab_api/hello.py
vocab_api-0.1.3.dist-info/LICENSE
vocab_api-0.1.3.dist-info/METADATA
vocab_api-0.1.3.dist-info/WHEEL
vocab_api-0.1.3.dist-info/top_level.txt
vocab_api-0.1.3.dist-info/RECORD
