Metadata-Version: 2.1
Name: vocab-api
Version: 0.1.3
Summary: vocab_api
Home-page: https://github.com/mohith01/vocab_api
Author: mohith01
Author-email: mohith01@gmail.com
License: UNKNOWN
Keywords: python,anki,api,words,vocab
Platform: UNKNOWN
Classifier: Development Status :: 1 - Planning
Classifier: Intended Audience :: Developers
Classifier: Programming Language :: Python :: 3
Classifier: Operating System :: Unix
Classifier: Operating System :: MacOS :: MacOS X
Classifier: Operating System :: Microsoft :: Windows
Requires-Dist: requests
Requires-Dist: bs4
